[
  {
    "file": "1.jpg",
    "source": "File:2nd Infantry Division, E-1 draw, Easy Red sector, Omaha Beach, D+1, June 7, 1944.jpg",
    "artist": "US Army Signal Corps",
    "license": "Public domain",
    "url": "https://commons.wikimedia.org/wiki/File%3A2nd%20Infantry%20Division%2C%20E-1%20draw%2C%20Easy%20Red%20sector%2C%20Omaha%20Beach%2C%20D%2B1%2C%20June%207%2C%201944.jpg"
  },
  {
    "file": "2.jpg",
    "source": "File:80th anniversary of D-Day and the Battle of Normandy - 04.jpg",
    "artist": "European Union",
    "license": "Attribution",
    "url": "https://commons.wikimedia.org/wiki/File%3A80th%20anniversary%20of%20D-Day%20and%20the%20Battle%20of%20Normandy%20-%2004.jpg"
  },
  {
    "file": "3.jpg",
    "source": "File:80th anniversary of D-Day and the Battle of Normandy - 08.jpg",
    "artist": "European Union",
    "license": "Attribution",
    "url": "https://commons.wikimedia.org/wiki/File%3A80th%20anniversary%20of%20D-Day%20and%20the%20Battle%20of%20Normandy%20-%2008.jpg"
  },
  {
    "file": "4.jpg",
    "source": "File:80th anniversary of D-Day and the Battle of Normandy - 09.jpg",
    "artist": "European Union",
    "license": "Attribution",
    "url": "https://commons.wikimedia.org/wiki/File%3A80th%20anniversary%20of%20D-Day%20and%20the%20Battle%20of%20Normandy%20-%2009.jpg"
  },
  {
    "file": "5.jpg",
    "source": "File:Normandy, France, D-day Omaha Beach.jpg",
    "artist": "Dupont66",
    "license": "CC BY 4.0",
    "url": "https://commons.wikimedia.org/wiki/File%3ANormandy%2C%20France%2C%20D-day%20Omaha%20Beach.jpg"
  },
  {
    "file": "6.jpg",
    "source": "File:80TH ANNIVERSARY OF D-DAY OMAHA BEACH (8447341).jpg",
    "artist": "U.S. Army Reserve photo by Sgt. 1st Class Austin Berner",
    "license": "Public domain",
    "url": "https://commons.wikimedia.org/wiki/File%3A80TH%20ANNIVERSARY%20OF%20D-DAY%20OMAHA%20BEACH%20(8447341).jpg"
  },
  {
    "file": "7.jpg",
    "source": "File:80TH ANNIVERSARY OF D-DAY OMAHA BEACH (8447385).jpg",
    "artist": "U.S. Army Reserve photo by Sgt. 1st Class Austin Berner",
    "license": "Public domain",
    "url": "https://commons.wikimedia.org/wiki/File%3A80TH%20ANNIVERSARY%20OF%20D-DAY%20OMAHA%20BEACH%20(8447385).jpg"
  },
  {
    "file": "8.jpg",
    "source": "File:80TH ANNIVERSARY OF D-DAY OMAHA BEACH (8447389).jpg",
    "artist": "U.S. Army Reserve photo by Sgt. 1st Class Austin Berner",
    "license": "Public domain",
    "url": "https://commons.wikimedia.org/wiki/File%3A80TH%20ANNIVERSARY%20OF%20D-DAY%20OMAHA%20BEACH%20(8447389).jpg"
  },
  {
    "file": "9.jpg",
    "source": "File:80TH ANNIVERSARY OF D-DAY OMAHA BEACH (8447391).jpg",
    "artist": "U.S. Army Reserve photo by Sgt. 1st Class Austin Berner",
    "license": "Public domain",
    "url": "https://commons.wikimedia.org/wiki/File%3A80TH%20ANNIVERSARY%20OF%20D-DAY%20OMAHA%20BEACH%20(8447391).jpg"
  },
  {
    "file": "10.jpg",
    "source": "File:80TH ANNIVERSARY OF D-DAY OMAHA BEACH (8447393).jpg",
    "artist": "U.S. Army Reserve photo by Sgt. 1st Class Austin Berner",
    "license": "Public domain",
    "url": "https://commons.wikimedia.org/wiki/File%3A80TH%20ANNIVERSARY%20OF%20D-DAY%20OMAHA%20BEACH%20(8447393).jpg"
  }
]